smartbear_tunnel/__init__.py
smartbear_tunnel/client.py
tests/__init__.py
tests/test_smartbear_tunnel.py
smartbear_tunnel_python-0.3.dist-info/METADATA
smartbear_tunnel_python-0.3.dist-info/WHEEL
smartbear_tunnel_python-0.3.dist-info/top_level.txt
smartbear_tunnel_python-0.3.dist-info/RECORD
