Metadata-Version: 2.1
Name: smartbear-tunnel-python
Version: 0.3
Summary: A Python package for automating the Smartbear SecureTunnel
Home-page: https://github.com/crossbrowsertesting/smartbear-tunnel-python
Author: Smartbear Software
Author-email: info@crossbrowsertesting.com
License: UNKNOWN
Platform: UNKNOWN
Classifier: Programming Language :: Python :: 3
Classifier: License :: OSI Approved :: MIT License
Classifier: Operating System :: OS Independent
Requires-Dist: requests (==2.26.0)
